{"is_source_file": false, "format": "", "description": "", "external_files": [], "external_methods": [], "published": [], "classes": [], "methods": [], "calls": [], "search-terms": [], "state": 2, "file_id": 1, "knowledge_revision": 5, "git_revision": "9ff6d2882a7371026c2aa9667f698f35fbb7fb9a", "hash": "de18056078b808f5e634e9f25b3ecca3", "format-version": 4, "code-base-name": "tic_tac_toe_frontend", "filename": "README.md", "revision_history": [{"5": "9ff6d2882a7371026c2aa9667f698f35fbb7fb9a"}]}